pyontoenv/__init__.py
pyontoenv-0.4.0.dist-info/WHEEL
pyontoenv-0.4.0.dist-info/METADATA
pyontoenv-0.4.0.dist-info/RECORD
