Metadata-Version: 2.3
Name: pyontoenv
Version: 0.4.0
Summary: Compatibility wrapper that installs the ontoenv package.
Author: Gabe Fierro
Author-email: Gabe Fierro <gtfierro@mines.edu>
License: BSD-3-Clause
Requires-Dist: ontoenv
Requires-Python: >=3.11
Project-URL: Homepage, https://github.com/gtfierro/ontoenv-rs
Project-URL: Issues, https://github.com/gtfierro/ontoenv-rs/issues
Project-URL: Repository, https://github.com/gtfierro/ontoenv-rs
